examples/__init__.py
examples/advanced_example_1_toui_blueprint.py
examples/advanced_example_2_toui_with_javascript.py
examples/advanced_example_3_toui_with_google_sign_in.py
examples/advanced_example_4_toui_with_firebase.py
examples/advanced_example_5_toui_with_sql_user_database.py
examples/example_1_simple_website.py
examples/example_2_simple_desktop_app.py
examples/example_3_updating_page.py
examples/example_4_function_with_arg.py
examples/example_5_user_variables.py
examples/example_6_quick_website.py
examples/example_7_quick_desktop_app.py
toui/__init__.py
toui/_cmd.py
toui/_defaults.py
toui/_helpers.py
toui/_javascript_templates.py
toui/_signals.py
toui/apps.py
toui/elements.py
toui/exceptions.py
toui/pages.py
toui/structure.py
toui-3.4.2.dist-info/LICENSE
toui-3.4.2.dist-info/METADATA
toui-3.4.2.dist-info/WHEEL
toui-3.4.2.dist-info/entry_points.txt
toui-3.4.2.dist-info/top_level.txt
toui-3.4.2.dist-info/RECORD
