Metadata-Version: 2.1
Name: toui
Version: 3.4.2
Summary: Creates user interfaces (websites and desktop apps) from HTML easily
Author: Mubarak Almehairbi
Classifier: Programming Language :: Python :: 3
Classifier: License :: OSI Approved :: MIT License
Classifier: Operating System :: OS Independent
License-File: LICENSE
Requires-Dist: beautifulsoup4 (<5,>=4.12.2)
Requires-Dist: Flask (<3,>=2.2.5)
Requires-Dist: flask-sock (<1,>=0.6.0)
Requires-Dist: pywebview (<5,>=4.1)
Requires-Dist: tinycss (<1,>=0.4)
Requires-Dist: requests (<3,>=2.31.0)
Requires-Dist: flask-sqlalchemy (<4,>=3.0.3)
Requires-Dist: Flask-BasicAuth (<1,>=0.2.0)
Requires-Dist: Flask-Login (<1,>=0.6.2)
Requires-Dist: firebase-admin (<7,>=6.2.0)
